a_trade_calendar/__init__.py
a_trade_calendar/a_trade_calendar.csv
a_trade_calendar/calendar_util.py
a_trade_calendar-2027.2.13.1.dist-info/METADATA
a_trade_calendar-2027.2.13.1.dist-info/WHEEL
a_trade_calendar-2027.2.13.1.dist-info/licenses/LICENSE
a_trade_calendar-2027.2.13.1.dist-info/RECORD
