Metadata-Version: 2.4
Name: a_trade_calendar
Version: 2027.2.13.1
Summary: 适用于A股，一款简单、纯粹的交易日历工具包。来自[西海岸量化工作室]。
License: BSD 2-Clause License
License-File: LICENSE
Keywords: a股,日历
